projen_types/__init__.py
projen_types/py.typed
projen_types/_jsii/__init__.py
projen_types/_jsii/projen-types@0.1.7.jsii.tgz
projen_types-0.1.7.dist-info/LICENSE
projen_types-0.1.7.dist-info/METADATA
projen_types-0.1.7.dist-info/WHEEL
projen_types-0.1.7.dist-info/top_level.txt
projen_types-0.1.7.dist-info/RECORD
