Metadata-Version: 2.1
Name: projen-types
Version: 0.1.7
Summary: My custom projen project types
Home-page: https://github.com/mnoumanshahzad/projen-types.git
Author: mnoumanshahzad<mnoumanshahzad@hotmail.com>
License: Apache-2.0
Project-URL: Source, https://github.com/mnoumanshahzad/projen-types.git
Platform: UNKNOWN
Classifier: Intended Audience :: Developers
Classifier: Operating System :: OS Independent
Classifier: Programming Language :: JavaScript
Classifier: Programming Language :: Python :: 3 :: Only
Classifier: Programming Language :: Python :: 3.7
Classifier: Programming Language :: Python :: 3.8
Classifier: Programming Language :: Python :: 3.9
Classifier: Programming Language :: Python :: 3.10
Classifier: Typing :: Typed
Classifier: Development Status :: 5 - Production/Stable
Classifier: License :: OSI Approved
Requires-Python: ~=3.7
License-File: LICENSE
Requires-Dist: jsii (<2.0.0,>=1.60.1)
Requires-Dist: projen (<0.59.0,>=0.58.2)
Requires-Dist: publication (>=0.0.3)
